dcord/__init__.py
dcord-0.2.dist-info/METADATA
dcord-0.2.dist-info/WHEEL
dcord-0.2.dist-info/top_level.txt
dcord-0.2.dist-info/RECORD
