Metadata-Version: 2.1
Name: dcord
Version: 0.2
Summary: Eris
Home-page: http://github.com/eris9/dcord
Author: Eris9/Sakurai07
Author-email: blzzardst0rm@gmail.com
License: MIT
Platform: UNKNOWN
